{
  "en": {
    "social":"Social Media",
    "address":"Address",
    "home":"Home",
    "armada_clinic":"Armada Clinic",
    "contact_button":"Get Free Quote",
    "contact":"Contact",
    "in_minutes":"In Minutes",
    "diagnosis":"Diagnosis And Cost",
    "success_message":"Your message was sent successfully.",
    "form_validation":" Please enter your name and phone!",
    "contact_header":"Contact Us",
    "photo_detail":" Please upload a photo of your teeth to get a more detailed quote. (FREE)",
    "message":"Your Message",
    "photo":"Photo (Optional)",
    "name":"Name Surname",
    "phone":"Phone",
    "language_BIG":"LANGUAGE",
    "contact_BIG":"CONTACT",
    "contact_us":"Get Free Quote",
    "about": "About",
    "treatments": "Treatments",
    "our_treatments_BIG": "TREATMENTS",
    "armada_smile_clinic":"Armada Smile Clinic",
    "readmore": "Read More",
    "posted_on": "Posted on",
    "send_BIG": "SEND",
    "Prev": "Prev",
    "Next": "Next",
    "Edit": "Edit",
    "Delete": "Delete",
    "Back": "Back",
    "Save": "Save",
    "Update": "Update",
    "Add": "Add",
    "Passive": "Passive",
    "Active": "Active",
    "Add-image": "Add image",
    "Successfully-completed": "Successfully completed.",
    "Successfully-deleted": "Successfully deleted",
    "Brand": "Armada-Smile",
    "Big-Brand": "ARMADA-SMILE",
    "Log-In": "Log In",
    "Log-out": "Log out",
    "Email": "Email",
    "Password": "Password",
    "Your-email": "Your email",
    "Your-password": "Your password",
    "Remember-me": "Remember me",
    "Contact": "Contact",
    "Forgot-password": "Forgot password ?",
    "Password-does-not-match": "Password does not match",
    "Renew-password": "Renew password",
    "Image": "Image"
  },
  "tr": {
    "social":"Sosyal Medya",
    "address":"Adres",
    "home":"Ana Sayfa",
    "armada_clinic":"Kliniklerimiz",
    "contact_button":"Gönder",
    "contact":"İletişim",
    "in_minutes":"",
    "diagnosis":"Bize Ulaşın",
    "success_message":"Mesajınız gönderildi",
    "form_validation":" Lütfen İsim ve Telefon Bilgilerini Girin!",
    "contact_header":"Bize Ulaşın",
    "photo_detail":"",
    "message":"Mesajınız",
    "photo":"Resim (Opsiyonel)",
    "name":"İsim Soyisim",
    "phone":"Telefon",
    "language_BIG":"DİL",
    "contact_BIG":"İLETİŞİM",
    "contact_us":"Bize Ulaşın",
    "about": "Hakkımızda",
    "treatments": "Tedaviler",
    "our_treatments_BIG": "TEDAVİLERİMİZ",
    "readmore": "Devamını oku",
    "posted_on": "Yayınlanan yer",
    "send_BIG": "GÖNDER",
    "Prev": "Önceki",
    "Next": "Sonraki",
    "Edit": "Düzenle",
    "Delete": "Sil",
    "Back": "Geri",
    "Save": "Kaydet",
    "Update": "Güncelle",
    "Add": "Ekle",
    "Passive": "Pasif",
    "Active": "Aktif",
    "Add-image": "Görsel ekle",
    "Successfully-completed": "İşlem başarı ile tamamlandı.",
    "Successfully-deleted": "Kayıt başarı ile silindi",
    "Brand": "Armada Smile",
    "Big-Brand": "ARMADA SMILE",
    "Log-In": "Giriş Yap",
    "Email": "E-Posta",
    "Password": "Şifre",
    "Your-email": "E-Posta adresiniz",
    "Your-password": "Şifreniz",
    "Remember-me": "Beni Hatırla",
    "Contact": "İletişim",
    "Forgot-password": "Şifreni mi unuttun ?",
    "Password-does-not-match": "Şifreler eşleşmiyor",
    "Renew-password": "Şifre değiştir",
    "Log-out": "Çıkış yap",
    "Image": "Görsel"
  }
}
